example/__init__.py
example/args.py
example/example_consumer.py
example/example_cron_producer.py
example/example_csi.py
example/example_producer.py
example/brokers/__init__.py
example/brokers/kafka_broker.py
example/brokers/rmq_broker.py
example/brokers/uni_log_broker.py
example/messages/__init__.py
example/messages/ender_after_answer_message.py
example/messages/ender_after_cron_answer_message.py
example/messages/ender_after_cron_input_message.py
example/messages/ender_after_input_message.py
example/messages/input_message.py
example/messages/some_external_message.py
example/waitings/__init__.py
example/waitings/common_db_wating.py
example/workers/__init__.py
example/workers/auto_retry_worker.py
example/workers/ender_after_cron_worker.py
example/workers/ender_after_input_worker.py
example/workers/input_worker.py
example/workers/my_super_cron_worker.py
ul_unipipeline/__init__.py
ul_unipipeline/args.py
ul_unipipeline/errors.py
ul_unipipeline/main.py
ul_unipipeline/py.typed
ul_unipipeline/run.py
ul_unipipeline/answer/__init__.py
ul_unipipeline/answer/uni_answer_message.py
ul_unipipeline/answer/uni_answer_params.py
ul_unipipeline/brokers/__init__.py
ul_unipipeline/brokers/uni_amqp_pika_broker.py
ul_unipipeline/brokers/uni_amqp_py_broker.py
ul_unipipeline/brokers/uni_broker.py
ul_unipipeline/brokers/uni_broker_consumer.py
ul_unipipeline/brokers/uni_kafka_broker.py
ul_unipipeline/brokers/uni_log_broker.py
ul_unipipeline/brokers/uni_memory_broker.py
ul_unipipeline/config/__init__.py
ul_unipipeline/config/uni_config.py
ul_unipipeline/definitions/__init__.py
ul_unipipeline/definitions/uni_broker_definition.py
ul_unipipeline/definitions/uni_codec_definition.py
ul_unipipeline/definitions/uni_cron_task_definition.py
ul_unipipeline/definitions/uni_definition.py
ul_unipipeline/definitions/uni_dynamic_definition.py
ul_unipipeline/definitions/uni_external_definition.py
ul_unipipeline/definitions/uni_message_definition.py
ul_unipipeline/definitions/uni_module_definition.py
ul_unipipeline-2.0.6.dist-info/LICENSE
ul_unipipeline-2.0.6.dist-info/METADATA
ul_unipipeline-2.0.6.dist-info/WHEEL
ul_unipipeline-2.0.6.dist-info/entry_points.txt
ul_unipipeline-2.0.6.dist-info/top_level.txt
ul_unipipeline-2.0.6.dist-info/RECORD
