Metadata-Version: 2.1
Name: ul-unipipeline
Version: 2.0.6
Summary: simple way to build the declarative and distributed data pipelines with python. it supports rabbitmq or kafka as a broker
Home-page: https://gitlab.neroelectronics.by/unic-lab/libraries/common-python-utils/unipipeline.git
Author: Unic-lab
Author-email: 
License: MIT
Classifier: Intended Audience :: Developers
Classifier: License :: OSI Approved :: MIT License
Classifier: Programming Language :: Python
Classifier: Programming Language :: Python :: 3.6
Classifier: Programming Language :: Python :: 3.7
Classifier: Programming Language :: Python :: 3.8
Classifier: Programming Language :: Python :: 3.9
Classifier: Programming Language :: Python :: 3.10
Classifier: Programming Language :: Python :: 3.11
Classifier: Operating System :: OS Independent
License-File: LICENSE
Requires-Dist: jinja2 (>=3.0.3)
Requires-Dist: amqp (>=5.1.1)
Requires-Dist: pyyaml (>=6.0)
Requires-Dist: types-pyyaml (>=6.0)
Requires-Dist: pydantic (==2.10.5)
Requires-Dist: psycopg2-binary (>=2.9.3)
Requires-Dist: pika (>=1.2.0)
Requires-Dist: crontab (>=0.23.0)
Requires-Dist: kafka-python (>=2.0.2)
